{"status":"OK","copyright":"Copyright (c) 2015 The New York Times Company.  All Rights Reserved.","num_results":15,"last_modified":"2015-07-04T06:31:58-04:00","results":{"list_name":"Culture","bestsellers_date":"2015-06-27","published_date":"2015-07-12","display_name":"Culture","normal_list_ends_at":10,"updated":"MONTHLY","books":[{"rank":1,"rank_last_week":0,"weeks_on_list":0,"asterisk":0,"dagger":0,"primary_isbn10":"1476762724","primary_isbn13":"9781476762722","publisher":"Simon & Schuster","description":"A memoir of life among the wealthy women of the Upper East Side, in the satirical guise of an anthropological study.","price":0,"title":"PRIMATES OF PARK AVENUE","author":"Wednesday Martin","contributor":"by Wednesday Martin","contributor_note":"","book_image":"http:\/\/du.ec2.nytimes.com.s3.amazonaws.com\/prd\/books\/9781476762722.jpg","amazon_product_url":"http:\/\/www.amazon.com\/Primates-Park-Avenue-A-Memoir-ebook\/dp\/B00P4348G0?tag=thenewyorktim-20","age_group":"","book_review_link":"","first_chapter_link":"","sunday_review_link":"","article_chapter_link":"","isbns":[{"isbn10":"1476762627","isbn13":"9781476762623"},{"isbn10":"1476762724","isbn13":"9781476762722"}]},{"rank":2,"rank_last_week":0,"weeks_on_list":0,"asterisk":0,"dagger":0,"primary_isbn10":"0062417444","primary_isbn13":"9780062417442","publisher":"Morrow","description":"A celebration of the resilience of the English language; first published in 1990 and just reissued.","price":0,"title":"THE MOTHER TONGUE","author":"Bill Bryson","contributor":"by Bill Bryson","contributor_note":"","book_image":"http:\/\/du.ec2.nytimes.com.s3.amazonaws.com\/prd\/books\/9780062417442.jpg","amazon_product_url":"http:\/\/www.amazon.com\/The-Mother-Tongue-English-that-ebook\/dp\/B00T3DR56C?tag=thenewyorktim-20","age_group":"","book_review_link":"","first_chapter_link":"","sunday_review_link":"","article_chapter_link":"","isbns":[{"isbn10":"0062417444","isbn13":"9780062417442"},{"isbn10":"0380715430","isbn13":"9780380715435"}]},{"rank":3,"rank_last_week":0,"weeks_on_list":0,"asterisk":0,"dagger":0,"primary_isbn10":"0316247766","primary_isbn13":"9780316247764","publisher":"Little, Brown","description":"The photographer\u2019s thoughts on art, photography, family and the South.","price":0,"title":"HOLD STILL","author":"Sally Mann","contributor":"by Sally Mann","contributor_note":"","book_image":"http:\/\/du.ec2.nytimes.com.s3.amazonaws.com\/prd\/books\/9780316247764.jpg","amazon_product_url":"http:\/\/www.amazon.com\/Hold-Still-A-Memoir-Photographs\/dp\/0316247766?tag=thenewyorktim-20","age_group":"","book_review_link":"","first_chapter_link":"","sunday_review_link":"http:\/\/www.nytimes.com\/2015\/05\/10\/books\/review\/hold-still-a-memoir-by-sally-mann.html","article_chapter_link":"","isbns":[{"isbn10":"0316247766","isbn13":"9780316247764"},{"isbn10":"031624774X","isbn13":"9780316247740"},{"isbn10":"1478933178","isbn13":"9781478933175"}]},{"rank":4,"rank_last_week":0,"weeks_on_list":0,"asterisk":0,"dagger":0,"primary_isbn10":"0984504176","primary_isbn13":"9780984504176","publisher":"South Dakota State Historical Society Press","description":"The writer\u2019s autobiography, the source of her Little House on the Prairie books, completed in 1930 and never published, is annotated by a biographer.","price":0,"title":"PIONEER GIRL","author":"Laura Ingalls Wilder","contributor":"by Laura Ingalls Wilder","contributor_note":"","book_image":"http:\/\/du.ec2.nytimes.com.s3.amazonaws.com\/prd\/books\/9780984504176.jpeg","amazon_product_url":"http:\/\/www.amazon.com\/Pioneer-Girl-The-Annotated-Autobiography\/dp\/0984504176?tag=thenewyorktim-20","age_group":"","book_review_link":"","first_chapter_link":"","sunday_review_link":"","article_chapter_link":"","isbns":[{"isbn10":"0984504176","isbn13":"9780984504176"}]},{"rank":5,"rank_last_week":0,"weeks_on_list":0,"asterisk":0,"dagger":0,"primary_isbn10":"147673075X","primary_isbn13":"9781476730752","publisher":"Simon & Schuster","description":"The Oscar-winning producer describes the importance of curiosity in his life, and how others can harness its power.","price":0,"title":"A CURIOUS MIND","author":"Brian Grazer and Charles Fishman","contributor":"by Brian Grazer and Charles Fishman","contributor_note":"","book_image":"http:\/\/du.ec2.nytimes.com.s3.amazonaws.com\/prd\/books\/9781476730790.jpg","amazon_product_url":"http:\/\/www.amazon.com\/Curious-Mind-Secret-Bigger-Life-ebook\/dp\/B00LJXK23C?tag=thenewyorktim-20","age_group":"","book_review_link":"","first_chapter_link":"","sunday_review_link":"","article_chapter_link":"","isbns":[{"isbn10":"147673075X","isbn13":"9781476730752"},{"isbn10":"1476730792","isbn13":"9781476730790"},{"isbn10":"1442382082","isbn13":"9781442382084"}]},{"rank":6,"rank_last_week":0,"weeks_on_list":0,"asterisk":0,"dagger":0,"primary_isbn10":"0393240185","primary_isbn13":"9780393240184","publisher":"Norton","description":"A memoir of a career in the New Yorker's storied copy department, along with grammar advice.","price":0,"title":"BETWEEN YOU & ME","author":"Mary Norris","contributor":"by Mary Norris","contributor_note":"","book_image":"http:\/\/du.ec2.nytimes.com.s3.amazonaws.com\/prd\/books\/9780393240184.jpg","amazon_product_url":"http:\/\/www.amazon.com\/Between-You-Me-Confessions-Comma\/dp\/0393240185?tag=thenewyorktim-20","age_group":"","book_review_link":"","first_chapter_link":"","sunday_review_link":"http:\/\/www.nytimes.com\/2015\/04\/19\/books\/review\/between-you-me-by-mary-norris.html","article_chapter_link":"","isbns":[{"isbn10":"0393240185","isbn13":"9780393240184"},{"isbn10":"0393246604","isbn13":"9780393246605"}]},{"rank":7,"rank_last_week":0,"weeks_on_list":0,"asterisk":0,"dagger":0,"primary_isbn10":"0143127667","primary_isbn13":"9780143127666","publisher":"Penguin Press","description":"The author\u2019s experience as Harper Lee\u2019s neighbor in small-town Monroeville, Ala.","price":0,"title":"THE MOCKINGBIRD NEXT DOOR","author":"Marja Mills","contributor":"by Marja Mills","contributor_note":"","book_image":"http:\/\/du.ec2.nytimes.com.s3.amazonaws.com\/prd\/books\/9780698163836.jpeg","amazon_product_url":"http:\/\/www.amazon.com\/The-Mockingbird-Next-Door-Harper-ebook\/dp\/B00G3L14KA?tag=thenewyorktim-20","age_group":"","book_review_link":"http:\/\/www.nytimes.com\/2014\/07\/18\/books\/the-mockingbird-next-door-by-marja-mills.html","first_chapter_link":"","sunday_review_link":"","article_chapter_link":"","isbns":[{"isbn10":"1594205191","isbn13":"9781594205194"},{"isbn10":"1410469743","isbn13":"9781410469748"},{"isbn10":"0143127667","isbn13":"9780143127666"}]},{"rank":8,"rank_last_week":0,"weeks_on_list":0,"asterisk":0,"dagger":0,"primary_isbn10":"0062316095","primary_isbn13":"9780062316097","publisher":"Harper","description":"How Homo sapiens became Earth\u2019s dominant species.","price":0,"title":"SAPIENS","author":"Yuval Noah Harari","contributor":"by Yuval Noah Harari","contributor_note":"","book_image":"http:\/\/du.ec2.nytimes.com.s3.amazonaws.com\/prd\/books\/9780062316097.jpeg","amazon_product_url":"http:\/\/www.amazon.com\/Sapiens-A-Brief-History-Humankind-ebook\/dp\/B00ICN066A?tag=thenewyorktim-20","age_group":"","book_review_link":"","first_chapter_link":"","sunday_review_link":"","article_chapter_link":"","isbns":[{"isbn10":"0062316095","isbn13":"9780062316097"},{"isbn10":"0062316109","isbn13":"9780062316103"}]},{"rank":9,"rank_last_week":0,"weeks_on_list":0,"asterisk":0,"dagger":0,"primary_isbn10":"0062282719","primary_isbn13":"9780062282712","publisher":"Harper Perennial\/HarperCollins","description":"A collection of essays on race, gender, politics and \"Sweet Valley High.\"","price":0,"title":"BAD FEMINIST","author":"Roxane Gay","contributor":"by Roxane Gay","contributor_note":"","book_image":"http:\/\/du.ec2.nytimes.com.s3.amazonaws.com\/prd\/books\/9780062282712.jpeg","amazon_product_url":"http:\/\/www.amazon.com\/Bad-Feminist-Essays-Roxane-Gay\/dp\/0062282719?tag=thenewyorktim-20","age_group":"","book_review_link":"","first_chapter_link":"","sunday_review_link":"http:\/\/www.nytimes.com\/2014\/10\/12\/books\/review\/daphne-merkins-the-fame-lunches-and-roxane-gays-bad-feminist.html","article_chapter_link":"","isbns":[{"isbn10":"0062282719","isbn13":"9780062282712"}]},{"rank":10,"rank_last_week":0,"weeks_on_list":0,"asterisk":0,"dagger":0,"primary_isbn10":"1555977073","primary_isbn13":"9781555977078","publisher":"Graywolf","description":"A memoir that explores the limits and possibilities of love and art, gender and identity, language and individual freedom in society, marriage and family-making.","price":0,"title":"THE ARGONAUTS","author":"Maggie Nelson","contributor":"by Maggie Nelson","contributor_note":"","book_image":"http:\/\/du.ec2.nytimes.com.s3.amazonaws.com\/prd\/books\/9781555977078.jpg","amazon_product_url":"http:\/\/www.amazon.com\/The-Argonauts-Maggie-Nelson\/dp\/1555977073?tag=thenewyorktim-20","age_group":"","book_review_link":"","first_chapter_link":"","sunday_review_link":"","article_chapter_link":"","isbns":[{"isbn10":"1555977073","isbn13":"9781555977078"}]},{"rank":11,"rank_last_week":0,"weeks_on_list":0,"asterisk":0,"dagger":0,"primary_isbn10":"0761169253","primary_isbn13":"9780761169253","publisher":"Workman","description":"Presenting 10 principles to help readers discover their artistic side.","price":0,"title":"STEAL LIKE AN ARTIST","author":"Austin Kleon","contributor":"by Austin Kleon","contributor_note":"","book_image":"http:\/\/du.ec2.nytimes.com.s3.amazonaws.com\/prd\/books\/9780761169253.jpeg","amazon_product_url":"http:\/\/www.amazon.com\/Steal-Like-Artist-Things-Creative\/dp\/0761169253?tag=thenewyorktim-20","age_group":"","book_review_link":"","first_chapter_link":"","sunday_review_link":"","article_chapter_link":"","isbns":[{"isbn10":"0761169253","isbn13":"9780761169253"}]},{"rank":12,"rank_last_week":0,"weeks_on_list":0,"asterisk":0,"dagger":0,"primary_isbn10":"1101873124","primary_isbn13":"9781101873120","publisher":"Vintage","description":"Gustav Klimt's 1907 portrait of Viennese socialite Adele Bloch-Bauer, its theft by Nazis during World War II and its subsequent lengthy disputed ownership.","price":0,"title":"THE LADY IN GOLD","author":"Anne-Marie O'Connor","contributor":"by Anne-Marie O'Connor","contributor_note":"","book_image":"http:\/\/du.ec2.nytimes.com.s3.amazonaws.com\/prd\/books\/9781101873120.jpg","amazon_product_url":"http:\/\/www.amazon.com\/The-Lady-Gold-Extraordinary-Masterpiece\/dp\/1101873124?tag=thenewyorktim-20","age_group":"","book_review_link":"","first_chapter_link":"","sunday_review_link":"","article_chapter_link":"","isbns":[{"isbn10":"1101873124","isbn13":"9781101873120"},{"isbn10":"030795756X","isbn13":"9780307957566"},{"isbn10":"0307265641","isbn13":"9780307265647"}]},{"rank":13,"rank_last_week":0,"weeks_on_list":0,"asterisk":0,"dagger":0,"primary_isbn10":"1439156816","primary_isbn13":"9781439156810","publisher":"Simon & Schuster","description":"A memoir that is a master class on the writer's craft.","price":0,"title":"ON WRITING","author":"Stephen King","contributor":"by Stephen King","contributor_note":"","book_image":"http:\/\/du.ec2.nytimes.com.s3.amazonaws.com\/prd\/books\/9781439156810.jpeg","amazon_product_url":"http:\/\/www.amazon.com\/On-Writing-Anniversary-Edition-Memoir\/dp\/1439156816?tag=thenewyorktim-20","age_group":"","book_review_link":"http:\/\/www.nytimes.com\/2000\/10\/05\/books\/books-of-the-times-how-to-write-if-you-re-stephen-king.html","first_chapter_link":"","sunday_review_link":"http:\/\/www.nytimes.com\/2000\/10\/08\/books\/making-it.html","article_chapter_link":"","isbns":[{"isbn10":"1439156816","isbn13":"9781439156810"},{"isbn10":"0743211537","isbn13":"9780743211536"},{"isbn10":"0684853523","isbn13":"9780684853529"},{"isbn10":"1439193630","isbn13":"9781439193631"}]},{"rank":14,"rank_last_week":0,"weeks_on_list":0,"asterisk":0,"dagger":0,"primary_isbn10":"194045025X","primary_isbn13":"9781940450254","publisher":"McSweeney's","description":"","price":0,"title":"WHITE GIRLS","author":"Hilton Als","contributor":"by Hilton Als","contributor_note":"","book_image":"http:\/\/du.ec2.nytimes.com.s3.amazonaws.com\/prd\/books\/9781940450254.jpeg","amazon_product_url":"http:\/\/www.amazon.com\/White-Girls-Hilton-Als\/dp\/194045025X?tag=thenewyorktim-20","age_group":"","book_review_link":"","first_chapter_link":"","sunday_review_link":"http:\/\/www.nytimes.com\/2013\/11\/10\/books\/review\/white-girls-by-hilton-als.html","article_chapter_link":"","isbns":[{"isbn10":"194045025X","isbn13":"9781940450254"},{"isbn10":"1936365812","isbn13":"9781936365814"},{"isbn10":"1940450063","isbn13":"9781940450063"}]},{"rank":15,"rank_last_week":0,"weeks_on_list":0,"asterisk":0,"dagger":0,"primary_isbn10":"0307592227","primary_isbn13":"9780307592224","publisher":"Broadway","description":"How a baffling and salacious murder case in 1897 New York City launched the tabloid media war of moguls Pulitzer and Hearst.","price":0,"title":"THE MURDER OF THE CENTURY","author":"Paul Collins","contributor":"by Paul Collins","contributor_note":"","book_image":"http:\/\/du.ec2.nytimes.com.s3.amazonaws.com\/prd\/books\/9780307592224.jpeg","amazon_product_url":"http:\/\/www.amazon.com\/The-Murder-Century-Scandalized-Sparked-ebook\/dp\/B004J4WLLE?tag=thenewyorktim-20","age_group":"","book_review_link":"","first_chapter_link":"","sunday_review_link":"","article_chapter_link":"","isbns":[{"isbn10":"0307592227","isbn13":"9780307592224"},{"isbn10":"0307592219","isbn13":"9780307592217"}]}],"corrections":[]}}